msaf2/__init__.py
msaf2/__main__.py
msaf2/config.py
msaf2/errors.py
msaf2/logger.py
msaf2/manager.py
msaf2/parser.py
msaf2/threader.py
msaf2/utils.py
msaf2/chai/__init__.py
msaf2/merge/__init__.py
msaf2-0.5.0.dist-info/METADATA
msaf2-0.5.0.dist-info/WHEEL
msaf2-0.5.0.dist-info/entry_points.txt
msaf2-0.5.0.dist-info/RECORD
