Metadata-Version: 2.4
Name: msaf2
Version: 0.5.0
Summary: Building and managing MSA prior to stucture inference
Author-email: Guillaume Launay <guillaume.launay@univ-lyon1.fr>
Requires-Python: >=3.12
Requires-Dist: biopython>=1.83
Requires-Dist: fastparquet>=2024.11.0
Requires-Dist: pandas>=2.2.3
Requires-Dist: pyyaml>=6.0.2
Requires-Dist: rich>=13.9.4
